seismic_attributes/seismic_attributes.py
seismic_attributes/test_seismic_attributes.py
seismic_attributes-1.0.5.dist-info/METADATA
seismic_attributes-1.0.5.dist-info/WHEEL
seismic_attributes-1.0.5.dist-info/top_level.txt
seismic_attributes-1.0.5.dist-info/RECORD
