Metadata-Version: 2.1
Name: seismic-attributes
Version: 1.0.5
Summary: An ObsPy library for event detection and seismic attribute calculation: preparing waveforms for automated analysis.
Author: Ross Turner
Author-email: turner.rj@icloud.com
Requires-Dist: numpy
Requires-Dist: pandas
Requires-Dist: matplotlib
Requires-Dist: obspy
Requires-Dist: pytz
Requires-Dist: seaborn
Requires-Dist: pytest
